LICENSE
MANIFEST.in
README.rst
setup.py
protolite/__init__.py
protolite/encoder.py
protolite/generator.py
protolite/serializer.py
protolite/util.py
protolite.egg-info/PKG-INFO
protolite.egg-info/SOURCES.txt
protolite.egg-info/dependency_links.txt
protolite.egg-info/entry_points.txt
protolite.egg-info/requires.txt
protolite.egg-info/top_level.txt
protolite/cli/__init__.py
protolite/cli/protolitec.py
protolite/parser/__init__.py
protolite/parser/proto_lexer.py
protolite/parser/proto_parser.py
protolite/test/__init__.py
protolite/test/test_encoder.py
protolite/test/test_serializer.py