Metadata-Version: 1.1
Name: protolite
Version: 0.1.0
Summary: ("Lightweight implementation of Google's Protocol Buffers in Python",)
Home-page: https://github.com/thelinuxkid/python-protolite
Author: Andy Gayton
Author-email: andy@thecablelounge.com
License: MIT
Platform: UNKNOWN
Classifier: Development Status :: 4 - Beta
Classifier: Intended Audience :: Developers
Classifier: Natural Language :: English
Classifier: License :: OSI Approved :: MIT License
Classifier: Programming Language :: Python
Classifier: Programming Language :: Python :: 2.7
